abstractvision/__init__.py
abstractvision-0.1.0.dist-info/licenses/LICENSE
abstractvision-0.1.0.dist-info/METADATA
abstractvision-0.1.0.dist-info/WHEEL
abstractvision-0.1.0.dist-info/top_level.txt
abstractvision-0.1.0.dist-info/RECORD
